Metadata-Version: 1.0
Name: forward-password
Version: 0.6
Summary: Manage passwords on the command line
Home-page: https://github.com/dicedtomatoreal/forward
Author: dicedtomato
Author-email: pranaco2@gmail.com
License: MIT
Platform: UNKNOWN
